DataPlatform_test/__init__.py
DataPlatform_test/main.py
DataPlatform_test/version.py
DataPlatformtest/__init__.py
DataPlatformtest/main.py
DataPlatform_test-0.2.8.dist-info/METADATA
DataPlatform_test-0.2.8.dist-info/WHEEL
DataPlatform_test-0.2.8.dist-info/entry_points.txt
DataPlatform_test-0.2.8.dist-info/top_level.txt
DataPlatform_test-0.2.8.dist-info/RECORD
